jupyterlab_autodocstring/__init__.py
jupyterlab_autodocstring/_version.py
jupyterlab_autodocstring/labextension/build_log.json
jupyterlab_autodocstring/labextension/package.json
jupyterlab_autodocstring/labextension/schemas/jupyterlab_autodocstring/package.json.orig
jupyterlab_autodocstring/labextension/schemas/jupyterlab_autodocstring/plugin.json
jupyterlab_autodocstring/labextension/static/lib_index_js.f827baad76e4d32ab7af.js
jupyterlab_autodocstring/labextension/static/lib_index_js.f827baad76e4d32ab7af.js.map
jupyterlab_autodocstring/labextension/static/remoteEntry.6b2ee860d1e365443929.js
jupyterlab_autodocstring/labextension/static/remoteEntry.6b2ee860d1e365443929.js.map
jupyterlab_autodocstring/labextension/static/style.js
jupyterlab_autodocstring/labextension/static/style_index_js.f10d60578ddf782aca04.js
jupyterlab_autodocstring/labextension/static/style_index_js.f10d60578ddf782aca04.js.map
jupyterlab_autodocstring-0.1.0.dist-info/LICENSE
jupyterlab_autodocstring-0.1.0.dist-info/METADATA
jupyterlab_autodocstring-0.1.0.dist-info/WHEEL
jupyterlab_autodocstring-0.1.0.dist-info/entry_points.txt
jupyterlab_autodocstring-0.1.0.dist-info/top_level.txt
jupyterlab_autodocstring-0.1.0.dist-info/RECORD
